README.md
setup.cfg
setup.py
cpp/__init__.py
cpp/cpp.py
cpp/cpp_e.py
cpp/datos_grid.py
cpp/ploteos.py
cpp/ploteos_e.py
cpp.egg-info/PKG-INFO
cpp.egg-info/SOURCES.txt
cpp.egg-info/dependency_links.txt
cpp.egg-info/requires.txt
cpp.egg-info/top_level.txt