Metadata-Version: 1.1
Name: cpp
Version: 1.0.0.6
Summary: Primera version de cpp!
Home-page: UNKNOWN
Author: UNKNOWN
Author-email: erick.alvarez.met@gmail.com
License: MIT
Download-URL: https://github.com/3r1ck10/cpp/archive/v1.0.0.tar.gz
Platform: UNKNOWN
Classifier: Development Status :: 3 - Alpha
Classifier: Intended Audience :: Developers
Classifier: Topic :: Software Development :: Build Tools
Classifier: License :: OSI Approved :: MIT License
Classifier: Programming Language :: Python :: 3
Classifier: Programming Language :: Python :: 3.4
Classifier: Programming Language :: Python :: 3.5
Classifier: Programming Language :: Python :: 3.6
